README.txt
bootstrap.py
buildout.cfg
setup.py
versions.cfg
collective/__init__.py
collective.piwik.flowplayer.egg-info/PKG-INFO
collective.piwik.flowplayer.egg-info/SOURCES.txt
collective.piwik.flowplayer.egg-info/dependency_links.txt
collective.piwik.flowplayer.egg-info/entry_points.txt
collective.piwik.flowplayer.egg-info/namespace_packages.txt
collective.piwik.flowplayer.egg-info/not-zip-safe
collective.piwik.flowplayer.egg-info/requires.txt
collective.piwik.flowplayer.egg-info/top_level.txt
collective/piwik/__init__.py
collective/piwik/flowplayer/__init__.py
collective/piwik/flowplayer/configure.zcml
collective/piwik/flowplayer/flow.pt
collective/piwik/flowplayer/star.pt
collective/piwik/flowplayer/tests.py
collective/piwik/flowplayer/version.txt
collective/piwik/flowplayer/view.py
collective/piwik/flowplayer/viewlets.py
docs/CONTRIBUTORS.txt
docs/HISTORY.txt
docs/INSTALL.txt
docs/LICENSE.GPL
docs/LICENSE.txt