Metadata-Version: 1.0
Name: collective.piwik.flowplayer
Version: 0.3
Summary: Analytics support for flowplayer using piwik
Home-page: http://svn.plone.org/svn/collective/collective.piwik.flowplayer
Author: unweb.me
Author-email: we@unweb.me
License: GPL
Keywords: video analytics flowplayer piwik plone
Platform: UNKNOWN
Classifier: Framework :: Plone
Classifier: Programming Language :: Python
